adk_chatkit/__about__.py
adk_chatkit/__init__.py
adk_chatkit/_client_tool_call.py
adk_chatkit/_constants.py
adk_chatkit/_context.py
adk_chatkit/_event_utils.py
adk_chatkit/_response.py
adk_chatkit/_store.py
adk_chatkit/_thread_utils.py
adk_chatkit/_widgets.py
adk_chatkit-0.0.6.dist-info/METADATA
adk_chatkit-0.0.6.dist-info/WHEEL
adk_chatkit-0.0.6.dist-info/RECORD
