Metadata-Version: 2.4
Name: adk-chatkit
Version: 0.0.6
Summary: OpenAI chatkit backend support for Google ADK
Project-URL: repository, https://github.com/ksachdeva/adk-chatkit
Author: Sachdeva, Kapil
Classifier: Intended Audience :: Developers
Classifier: License :: OSI Approved :: Apache Software License
Classifier: Operating System :: OS Independent
Classifier: Programming Language :: Python
Classifier: Programming Language :: Python :: 3
Classifier: Programming Language :: Python :: 3.11
Classifier: Programming Language :: Python :: 3.12
Classifier: Programming Language :: Python :: 3.13
Classifier: Programming Language :: Python :: 3.14
Classifier: Topic :: Software Development :: Libraries :: Python Modules
Requires-Python: >=3.11
Requires-Dist: google-adk>=1.16.0
Requires-Dist: openai-chatkit>=1.1.0
Requires-Dist: pydantic>=2.11.7
